LICENSE
MANIFEST.in
README.rst
setup.py
cielo_webservice/__init__.py
cielo_webservice/adapter.py
cielo_webservice/exceptions.py
cielo_webservice/models.py
cielo_webservice/request.py
cielo_webservice/templates/cancelamento.xml
cielo_webservice/templates/captura.xml
cielo_webservice/templates/consulta.xml
cielo_webservice/templates/token.xml
cielo_webservice/templates/transacao.xml
docs/api.rst
docs/index.rst
docs/tutorial.rst
python_cielo_webservice.egg-info/PKG-INFO
python_cielo_webservice.egg-info/SOURCES.txt
python_cielo_webservice.egg-info/dependency_links.txt
python_cielo_webservice.egg-info/not-zip-safe
python_cielo_webservice.egg-info/requires.txt
python_cielo_webservice.egg-info/top_level.txt
tests/__init__.py
tests/test_models.py
tests/test_request.py