Metadata-Version: 1.1
Name: python-cielo-webservice
Version: 1.0.5
Summary: Biblioteca para trabalhar com a versão Webservice 1.5 da Cielo.
Home-page: https://github.com/allisson/python-cielo-webservice
Author: Allisson Azevedo
Author-email: allisson@gmail.com
License: MIT
Keywords: Payment,Payment Gateway,Cielo
Platform: UNKNOWN
Classifier: Intended Audience :: Developers
Classifier: Intended Audience :: System Administrators
Classifier: Operating System :: OS Independent
Classifier: Topic :: Software Development
Classifier: Programming Language :: Python :: 2.7
Classifier: Programming Language :: Python :: 3.3
Classifier: Programming Language :: Python :: 3.4
Classifier: Programming Language :: Python :: 3.5
Classifier: License :: OSI Approved :: MIT License
